pyskybitz/__init__.py
pyskybitz/config.py
pyskybitz/models/__init__.py
pyskybitz/models/base.py
pyskybitz/services/__init__.py
pyskybitz/services/api.py
pyskybitz/services/parser.py
pyskybitz-0.1.6.dist-info/WHEEL
pyskybitz-0.1.6.dist-info/METADATA
pyskybitz-0.1.6.dist-info/RECORD
