Metadata-Version: 2.1
Name: pyskybitz
Version: 0.1.6
Summary: Python client to work with SkyBitz API
Author: Jasurbek Nurboyev
Author-email: jasurbeknurboyev@gmail.com
Requires-Python: >=3.9,<4.0
Classifier: Programming Language :: Python :: 3
Classifier: Programming Language :: Python :: 3.10
Classifier: Programming Language :: Python :: 3.9
Provides-Extra: codegen
Requires-Dist: Inject (>=4.3.1,<5.0.0)
Requires-Dist: lxml (>=4.9.2,<5.0.0)
Requires-Dist: pydantic (>=1.10.4,<2.0.0)
Requires-Dist: requests (>=2.28.1,<3.0.0)
Requires-Dist: six (==1.16.0)
